[
    {
        "title": "如果不为生活发愁，你最想做什么",
        "author": "liyishi",
        "link": "https://bbs.byr.cn/article/WorkLife/1061673",
        "pubDate": "Wed, 21 Dec 2016 23:19:03 GMT",
        "description": "发信人: liyishi (qingxuren), 信区: WorkLife<br/>标题: 如果不为生活发愁，你最想做什么<br/>发信站: 北邮人论坛 (Tue Dec 20 22:14:34 2016), 站内<br/><br/>如题。<br/>--<br/><br/>※ 来源:·北邮人论坛 <a target=\"_blank\" href=\"http://bbs.byr.cn\">http://bbs.byr.cn</a>·[FROM: 221.205.162.*]<br/>"
    },
    {
        "title": "母亲，您在天堂可安好？",
        "author": "wiseking",
        "link": "https://bbs.byr.cn/article/Feeling/2956310",
        "pubDate": "Wed, 21 Dec 2016 17:17:36 GMT",
        "description": "发信人: wiseking (wiseking), 信区: Feeling<br/>标题: 母亲，您在天堂可安好？<br/>发信站: 北邮人论坛 (Mon Dec 19 19:07:00 2016), 站内<br/><br/>母亲，您遭受了三个半月病症折磨，最终还是在我怀里无声地离去了，我永远忘不了那种无能为力看着您逝去的感觉，恐惧？迷茫？彷徨？我也不知道，只是觉得心里永远有一个巨大的空洞无法填补了！<br/>母亲，您现在不痛了吧？可是我和弟弟还有父亲却没有您在身边了，现在您寂寞安静地葬在荒山上，可知我多心疼？您冷吗？您寂寞吗？回来看看我们吧！您为何如此要强，您到逝去那一刻都不曾发出一丝呻吟。<br/>母亲，与我梦中团聚吧！有什么未了的心愿告诉我啊！请您保佑弟弟和父亲啊，让他们健健康康平平安安吧！<br/> 世间之事，唯有孝不可等待，我切身体会了什么叫做子欲养而亲不在，这辈子以后都没有妈妈了。没有人给我做饭了，没有人给我洗衣了，没有人再打电话跟我唠叨了……<br/>各位， 珍惜今生的缘分吧，再无来世的相逢……<br/> 悼念亡母，母亲，永别了；母亲，安息吧！<br/>--<br/><br/>※ 来源:·<a target=\"_blank\" href=\"http://developers.byr.cn/mobile\">北邮人论坛手机客户端</a> bbs.byr.cn·[FROM: 117.135.229.*]<br/>"
    },
    {
        "title": "这文案，是不是可以给满分",
        "author": "BaconTin",
        "link": "https://bbs.byr.cn/article/Picture/3168345",
        "pubDate": "Wed, 21 Dec 2016 19:23:23 GMT",
        "description": "发信人: BaconTin (Bacon|粤广茶餐厅|非典型码农), 信区: Picture<br/>标题: 这文案，是不是可以给满分<br/>发信站: 北邮人论坛 (Thu Dec 22 00:14:14 2016), 站内<br/><br/><br /><a target=\"_blank\" href=\"/att/Picture/3168345/253\"><img border=\"0\" title=\"QQ图片20161222001327.png\" src=\"/att/Picture/3168345/253\" alt=\"QQ图片20161222001327.png\" class=\"resizeable\" /></a><br/>--<br/><br/>※ 来源:·北邮人论坛 <a target=\"_blank\" href=\"http://bbs.byr.cn\">http://bbs.byr.cn</a>·[FROM: 10.104.252.*]<br/><br/>"
    },
    {
        "title": "把帅气暖男征一个相伴一生的人",
        "author": "xiaokaixin",
        "link": "https://bbs.byr.cn/article/Friends/1782421",
        "pubDate": "Wed, 21 Dec 2016 23:22:51 GMT",
        "description": "发信人: xiaokaixin (我不听，我还是个宝宝), 信区: Friends<br/>标题: 把帅气暖男征一个相伴一生的人<br/>发信站: 北邮人论坛 (Wed Dec 21 16:51:38 2016), 站内<br/><br/>刚帮哥们蒸了，现在我又来了，来帮同事蒸一波，想来功德无量。<br/>重点大学本硕毕业，从事技术工作，收入不菲，典型潜力股。喜欢电影，喜欢旅行，爱好美食，爱好烹饪。会照顾人，对女朋友好，用情专一，家庭幸福温馨，无家庭负担。身高179，体型标准。<br/>希望女孩不超过92年，家庭不需要多么富裕，但是家庭必须幸福有爱。长相中上吧。<br/>具体q聊，3559493430。有时候工作忙，不及时回复，并不是因为傲慢。真诚交友，不要错过哦。<br/><br/><br/><br/><a target=\"_blank\" href=\"http://guiyou.wangx.in\">发自「贵邮」</a><br/>--<br/><br/>※ 来源:·北邮人论坛 <a target=\"_blank\" href=\"http://bbs.byr.cn\">http://bbs.byr.cn</a>·[FROM: 114.242.248.*]<br/><br/><br /><a target=\"_blank\" href=\"/att/Friends/1782421/675\"><img border=\"0\" title=\"photo_1482310291_2.jpg\" src=\"/att/Friends/1782421/675\" alt=\"photo_1482310291_2.jpg\" class=\"resizeable\" /></a><br /><a target=\"_blank\" href=\"/att/Friends/1782421/68354\"><img border=\"0\" title=\"photo_1482310291_1.jpg\" src=\"/att/Friends/1782421/68354\" alt=\"photo_1482310291_1.jpg\" class=\"resizeable\" /></a>"
    },
    {
        "title": "今天你吃饺子了吗？",
        "author": "alicegreen",
        "link": "https://bbs.byr.cn/article/Food/475377",
        "pubDate": "Wed, 21 Dec 2016 22:54:00 GMT",
        "description": "发信人: alicegreen (一碗红尘丨一只荔枝), 信区: Food<br/>标题: 今天你吃饺子了吗？<br/>发信站: 北邮人论坛 (Wed Dec 21 20:34:04 2016), 站内<br/><br/>朋友圈刷屏地晒饺子，没有吃饺子的飘过~<br/>--<br/><br/>※ 来源:·北邮人论坛 <a target=\"_blank\" href=\"http://bbs.byr.cn\">http://bbs.byr.cn</a>·[FROM: 10.208.7.*]<br/>"
    },
    {
        "title": "求小伙伴相约每月读一本书，相互监督，读完交流想法",
        "author": "danbai",
        "link": "https://bbs.byr.cn/article/Reading/52413",
        "pubDate": "Wed, 21 Dec 2016 23:28:34 GMT",
        "description": "发信人: danbai (Zoe), 信区: Reading<br/>标题: 求小伙伴相约每月读一本书，相互监督，读完交流想法<br/>发信站: 北邮人论坛 (Sat Dec 17 23:40:00 2016), 站内<br/><br/>感觉最近越来越浮躁鸟，书都看不下去了，一年都读不了几本书，所以求一个小伙伴，大家相互监督，每个月读一本书，读完一起交流想法……<br/>--<br/>啊啊啊，好久没上论坛，竟然这么多小伙伴，马上建群<br/>为什么不能上传附件了，求解答，二维码发不上来啊<br/>※ 修改:·danbai 于 Dec 21 18:37:26 2016 修改本文·[FROM: 10.28.133.*]<br/>※ 来源:·<a target=\"_blank\" href=\"http://developers.byr.cn/mobile\">北邮人论坛手机客户端</a> bbs.byr.cn·[FROM: 10.203.41.*]<br/>"
    },
    {
        "title": "有没有上过信息科学原理的学长",
        "author": "yxc7788",
        "link": "https://bbs.byr.cn/article/AimBUPT/102007",
        "pubDate": "Wed, 21 Dec 2016 17:50:37 GMT",
        "description": "发信人: yxc7788 (小萌科), 信区: AimBUPT<br/>标题: 有没有上过信息科学原理的学长<br/>发信站: 北邮人论坛 (Sat Dec 10 23:00:37 2016), 站内<br/><br/>这门课该怎么复习啊 考试好过吗<br/>--<br/><br/>※ 来源:·<a target=\"_blank\" href=\"http://developers.byr.cn/mobile\">北邮人论坛手机客户端</a> bbs.byr.cn·[FROM: 10.205.24.*]<br/>"
    },
    {
        "title": "为啥现在游泳馆不放音乐了啊",
        "author": "gogoshj",
        "link": "https://bbs.byr.cn/article/Swim/122719",
        "pubDate": "Wed, 21 Dec 2016 22:51:04 GMT",
        "description": "发信人: gogoshj (灬蓝雨灬), 信区: Swim<br/>标题: 为啥现在游泳馆不放音乐了啊<br/>发信站: 北邮人论坛 (Wed Dec 21 10:26:54 2016), 站内<br/><br/>好怀念以前游泳馆放音乐的时候，游累了就趴着听会歌，偶尔还能遇上自己喜欢的歌。。<br/><br/>为啥现在都不放音乐了啊<img src=\"/img/ubb/emc/21.gif\" alt=\"emc21\" style=\"display:inline;border-style:none\"/><br/><br/><br/><br/><br/><br/><a target=\"_blank\" href=\"http://guiyou.wangx.in\">发自「贵邮」</a><br/>※ 修改:·gogoshj 于 Dec 21 10:28:28 2016 修改本文·[FROM: 223.104.3.*]<br/>※ 来源:·北邮人论坛 <a target=\"_blank\" href=\"http://bbs.byr.cn\">http://bbs.byr.cn</a>·[FROM: 223.104.3.*]<br/>"
    },
    {
        "title": "额，问下有人愿意做手工书吗~",
        "author": "Jeanrry",
        "link": "https://bbs.byr.cn/article/DIYLife/45720",
        "pubDate": "Wed, 21 Dec 2016 18:56:39 GMT",
        "description": "发信人: Jeanrry (younger), 信区: DIYLife<br/>标题: 额，问下有人愿意做手工书吗~<br/>发信站: 北邮人论坛 (Thu Dec 22 01:08:38 2016), 站内<br/><br/>有的话年底约一波_(:_」∠)_<br/>※ 修改:·Jeanrry 于 Dec 22 01:10:03 2016 修改本文·[FROM: 223.104.38.*]<br/>※ 来源:·北邮人论坛 <a target=\"_blank\" href=\"http://bbs.byr.cn\">http://bbs.byr.cn</a>·[FROM: 223.104.38.*]<br/>"
    },
    {
        "title": "大家学历照都拍得怎么样。。",
        "author": "preston",
        "link": "https://bbs.byr.cn/article/Talking/5879828",
        "pubDate": "Wed, 21 Dec 2016 22:56:06 GMT",
        "description": "发信人: preston (妩媚的灭绝师太), 信区: Talking<br/>标题: 大家学历照都拍得怎么样。。<br/>发信站: 北邮人论坛 (Wed Dec 21 23:46:10 2016), 站内<br/><br/>刚上学信网看到，丑哭了啊。<br/>有没有办法换啊。。<br/><img src=\"/img/ubb/ema/1.gif\" alt=\"ema1\" style=\"display:inline;border-style:none\"/><img src=\"/img/ubb/ema/1.gif\" alt=\"ema1\" style=\"display:inline;border-style:none\"/><br/><br/><a target=\"_blank\" href=\"http://iwoyou.duapp.com\">通过『我邮2.0』发布</a><br/>--<br/><br/>※ 来源:·北邮人论坛 <a target=\"_blank\" href=\"http://bbs.byr.cn\">http://bbs.byr.cn</a>·[FROM: 10.202.14.*]<br/>"
    }
]